tenkn.py
tenkn-1.0.0.dist-info/LICENSE
tenkn-1.0.0.dist-info/METADATA
tenkn-1.0.0.dist-info/WHEEL
tenkn-1.0.0.dist-info/top_level.txt
tenkn-1.0.0.dist-info/RECORD
